django_rlog/__init__.py
django_rlog/defaults.py
django_rlog/logger.py
django_rlog/management/__init__.py
django_rlog/management/commands/__init__.py
django_rlog/management/commands/_arguments.py
django_rlog/management/commands/rlistlog.py
django_rlog/management/commands/rlog.py
django_rlog/management/commands/rstop.py
django_rlog-1.0.6.dist-info/DESCRIPTION.rst
django_rlog-1.0.6.dist-info/METADATA
django_rlog-1.0.6.dist-info/RECORD
django_rlog-1.0.6.dist-info/WHEEL
django_rlog-1.0.6.dist-info/metadata.json
django_rlog-1.0.6.dist-info/top_level.txt
